talisman_ie_ml_utils-0.1.0.data/data/VERSION
tie_ml_utils/__init__.py
tie_ml_utils/env.py
tie_ml_utils/helper.py
tie_ml_utils/torch_wrapper.py
tie_ml_utils/modules/__init__.py
tie_ml_utils/modules/feature_extractor/__init__.py
tie_ml_utils/modules/feature_extractor/batching.py
tie_ml_utils/modules/feature_extractor/helper.py
tie_ml_utils/modules/feature_extractor/tokenization.py
tie_ml_utils/modules/pooler/__init__.py
tie_ml_utils/modules/pooler/abstract.py
tie_ml_utils/modules/pooler/aggregate.py
tie_ml_utils/modules/pooler/attention.py
tie_ml_utils/modules/pooler/concat.py
tie_ml_utils/modules/pooler/configuration.py
tie_ml_utils/modules/pooler/select.py
tie_ml_utils/modules/sequence_tagger/__init__.py
tie_ml_utils/modules/sequence_tagger/decoder/__init__.py
tie_ml_utils/modules/sequence_tagger/decoder/labelling_strategy.py
tie_ml_utils/tools/__init__.py
tie_ml_utils/tools/memory_management.py
tie_ml_utils/tools/optimization.py
talisman_ie_ml_utils-0.1.0.dist-info/METADATA
talisman_ie_ml_utils-0.1.0.dist-info/WHEEL
talisman_ie_ml_utils-0.1.0.dist-info/top_level.txt
talisman_ie_ml_utils-0.1.0.dist-info/RECORD
