Metadata-Version: 2.4
Name: talisman-ie-ml-utils
Version: 0.1.0
Summary: Talisman-IE ML utilities
Author: ISPRAS Talisman NLP team
Author-email: modis@ispras.ru
Maintainer: Vladimir Mayorov
Maintainer-email: vmayorov@ispras.ru
License: Apache Software License
Classifier: Development Status :: 3 - Alpha
Classifier: Programming Language :: Python :: 3
Classifier: Programming Language :: Python :: 3.10
Classifier: Programming Language :: Python :: 3.11
Classifier: Intended Audience :: Developers
Classifier: Operating System :: OS Independent
Classifier: License :: OSI Approved :: Apache Software License
Requires-Python: >=3.10
Requires-Dist: talisman-interfaces<0.12,>=0.8
Requires-Dist: talisman-ie-datamodel<0.7,>=0.6.11
Requires-Dist: talisman-tools<0.12,>=0.10
Requires-Dist: talisman-dm<2,>=1.3.1
Requires-Dist: torch~=2.1
Requires-Dist: numpy<3,>=1.23.5
Requires-Dist: typing-extensions>=4.0.0
Requires-Dist: pynvml~=11.5
Dynamic: author
Dynamic: author-email
Dynamic: classifier
Dynamic: description-content-type
Dynamic: license
Dynamic: maintainer
Dynamic: maintainer-email
Dynamic: requires-dist
Dynamic: requires-python
Dynamic: summary
